{
  "$schema": "https://raw.githubusercontent.com/microsoft/vcpkg-tool/main/docs/vcpkg.schema.json",
  "name": "messenger-client",
  "version": "1.0.0",
  "dependencies": [
    {
      "name": "boost-asio",
      "features": [
        "ssl"
      ]
    },
    {
      "name": "boost-dll"
    },
    {
      "name": "boost-filesystem"
    },
    {
      "name": "boost-json"
    },
    {
      "name": "boost-algorithm"
    },
    {
      "name": "spdlog"
    }
  ],
  "builtin-baseline": "a4275b7eee79fb24ec2e135481ef5fce8b41c339"
}
